yaml2cli/__init__.py
yaml2cli/yaml2cli.py
yaml2cli-1.0.3.dist-info/LICENCE.md
yaml2cli-1.0.3.dist-info/METADATA
yaml2cli-1.0.3.dist-info/WHEEL
yaml2cli-1.0.3.dist-info/entry_points.txt
yaml2cli-1.0.3.dist-info/top_level.txt
yaml2cli-1.0.3.dist-info/RECORD
